Metadata-Version: 2.1
Name: odoo-addon-fleet_vehicle_log_fuel
Version: 18.0.1.0.0.7
Requires-Python: >=3.10
Requires-Dist: odoo==18.0.*
Summary: Add Log Fuels for your vehicles.
Home-page: https://github.com/OCA/fleet
License: AGPL-3
Author: ForgeFlow, Tecnativa, Odoo Community Association (OCA)
Author-email: support@odoo-community.org
Classifier: Programming Language :: Python
Classifier: Framework :: Odoo
Classifier: Framework :: Odoo :: 18.0
Classifier: License :: OSI Approved :: GNU Affero General Public License v3
